latch_gcp/__init__.py
latch_gcp/client_pool.py
latch_gcp/pubsub.py
latch_gcp/py.typed
latch_gcp/storage.py
latch_gcp-0.1.2.dist-info/LICENSE
latch_gcp-0.1.2.dist-info/METADATA
latch_gcp-0.1.2.dist-info/WHEEL
latch_gcp-0.1.2.dist-info/RECORD
